{
  "regions": {
    "US": {
      "name": "Mickey's Speedway USA (U)",
      "size": 0,
      "hashes": {
        "crc32": "",
        "md5": "",
        "sha1": ""
      },
      "addresses": {
        "PlayerState": "0x80123456",
        "HandleInput": "0x80124500",
        "SpawnObject": "0x8012A000",
        "ObjectListStart": "0x80300000"
      }
    },
    "JP": {
      "name": "Mickey's Speedway USA (J)",
      "addresses": {}
    },
    "EU": {
      "name": "Mickey's Speedway USA (E)",
      "addresses": {}
    }
  }
}